example_rules/__init__.py
example_rules/file_based_rule.py
example_rules/indentation_sensitive_rule.py
example_rules/line_based_rule.py
example_rules/rule_with_settings.py
example_rules/self_disabling_rule.py
example_rules/srcml_based_rule.py
rulecheck/__init__.py
rulecheck/__main__.py
rulecheck/engine.py
rulecheck/file.py
rulecheck/file_manager.py
rulecheck/ignore.py
rulecheck/logger.py
rulecheck/rule.py
rulecheck/rule_manager.py
rulecheck/srcml.py
tests/integration/__init__.py
tests/integration/test_command_line.py
tests/integration/test_file_selection.py
tests/integration/test_rule_execution.py
tests/rulepack1/__init__.py
tests/rulepack1/findIfStatements.py
tests/rulepack1/findSingleLineCommentsWith.py
tests/rulepack1/printFilename.py
tests/rulepack1/printLanguage.py
tests/rulepack1/printRowsWithWord.py
tests/rulepack2/__init__.py
tests/rulepack2/badRuleThrowsException.py
tests/rulepack2/rule1.py
tests/rulepack2/rule2.py
rulecheck-0.6.1.dist-info/LICENSE
rulecheck-0.6.1.dist-info/METADATA
rulecheck-0.6.1.dist-info/WHEEL
rulecheck-0.6.1.dist-info/entry_points.txt
rulecheck-0.6.1.dist-info/top_level.txt
rulecheck-0.6.1.dist-info/RECORD
