Metadata-Version: 2.1
Name: rulecheck
Version: 0.6.1
Summary: Utility to check source code against coding convention rules.
Home-page: https://github.com/e-shreve/rulecheck
Author: Erik Shreve
Author-email: e-shreve@users.noreply.github.com
License: MIT
Platform: UNKNOWN
Classifier: Development Status :: 3 - Alpha
Classifier: Environment :: Console
Classifier: Intended Audience :: Developers
Classifier: Intended Audience :: System Administrators
Classifier: License :: OSI Approved :: MIT License
Classifier: Operating System :: OS Independent
Classifier: Natural Language :: English
Classifier: Programming Language :: C
Classifier: Programming Language :: C++
Classifier: Programming Language :: Java
Classifier: Programming Language :: C#
Classifier: Topic :: Utilities
Requires-Dist: lxml
